blite/__init__.py
blite/httpCodes.py
blite/lib.py
blite/logger.py
blite/utils.py
blite-1.1.1.dist-info/METADATA
blite-1.1.1.dist-info/WHEEL
blite-1.1.1.dist-info/top_level.txt
blite-1.1.1.dist-info/RECORD
