Metadata-Version: 2.4
Name: blite
Version: 1.1.1
Summary: Minimal web backend framework
Author-email: ryzeon-dev <master@ryzeon.net>
Classifier: Programming Language :: Python :: 3
Classifier: Operating System :: OS Independent
Requires-Python: >=3.8
